epdnorway/__init__.py
epdnorway/epdnorway.py
epdnorway-0.3.dist-info/LICENSE
epdnorway-0.3.dist-info/METADATA
epdnorway-0.3.dist-info/WHEEL
epdnorway-0.3.dist-info/top_level.txt
epdnorway-0.3.dist-info/RECORD
