Metadata-Version: 2.1
Name: epdnorway
Version: 0.3
Summary: Extract and organize datapoints from Epd Norway DataSet
Home-page: https://bitbucket.com/knakk/epdnorway
Author: Knakk AS
Author-email: benjamin@knakk.no
License: MIT
Platform: UNKNOWN
Requires-Python: >=3.7
Requires-Dist: xmltodict
